README.rst
setup.py
snipeitv2/Accessories.py
snipeitv2/Assets.py
snipeitv2/AssetsMaintenances.py
snipeitv2/Categories.py
snipeitv2/Company.py
snipeitv2/Components.py
snipeitv2/Consumables.py
snipeitv2/DataUtil.py
snipeitv2/Fieldsets.py
snipeitv2/Licenses.py
snipeitv2/Locations.py
snipeitv2/Maintenances.py
snipeitv2/Manufacturers.py
snipeitv2/Models.py
snipeitv2/StatusLabels.py
snipeitv2/Users.py
snipeitv2/__init__.py
snipeitv2.egg-info/PKG-INFO
snipeitv2.egg-info/SOURCES.txt
snipeitv2.egg-info/dependency_links.txt
snipeitv2.egg-info/not-zip-safe
snipeitv2.egg-info/requires.txt
snipeitv2.egg-info/top_level.txt