Metadata-Version: 2.1
Name: snipeitv2
Version: 2.1.3
Summary: Python library to access the SnipeIT API
Home-page: https://github.com/allen-nathanield/SnipeIT-PythonAPI
Author: Nathan Allen
Author-email: allen.nathanield@gmail.com
License: MIT
Platform: UNKNOWN
